AspireTUI/ColorAndText.py
AspireTUI/Internet.py
AspireTUI/Lists.py
AspireTUI/OS.py
AspireTUI/Path.py
AspireTUI/Strings.py
AspireTUI/_PrintUtils.py
AspireTUI/_VersionInfo.py
AspireTUI/__init__.py
AspireTUI/_internal.py
AspireTUI/tui.py
AspireTUI/Classes/_Animation.py
AspireTUI/Classes/_AppManager.py
AspireTUI/Classes/_Conf copy.py
AspireTUI/Classes/_Conf.py
AspireTUI/Classes/_Crashlog.py
AspireTUI/Classes/_Log.py
AspireTUI/Classes/__init__.py
AspireTUI/Classes/_shared.py
AspireTUI/_MESSAGES/__init__.py
AspireTUI/_MESSAGES/english.py
AspireTUI/_theme/__init__.py
AspireTUI/_theme/styles.py
AspireTUI-0.5.1.dist-info/LICENSE.txt
AspireTUI-0.5.1.dist-info/METADATA
AspireTUI-0.5.1.dist-info/WHEEL
AspireTUI-0.5.1.dist-info/top_level.txt
AspireTUI-0.5.1.dist-info/RECORD
