Metadata-Version: 2.1
Name: AspireTUI
Version: 0.5.1
Summary: Achieving Seamless Performance In Real-time Environments : A framework for a line based TUI
Author-email: Simon Arjuna Erat <erat.simon@gmail.com>
License: MIT License
Project-URL: Homepage, https://github.com/sri-arjuna/ASPIRE
Project-URL: Bug Reports, https://github.com/sri-arjuna/ASPIRE/issues
Project-URL: Source, https://github.com/sri-arjuna/ASPIRE/
Project-URL: Help / Manual, https://github.com/sri-arjuna/ASPIRE/tree/master/docs/help
Keywords: TUI,console
Classifier: Development Status :: 3 - Alpha
Classifier: Intended Audience :: Developers
Classifier: Environment :: Console
Classifier: Topic :: Software Development :: Libraries :: Application Frameworks
Classifier: Topic :: System :: Shells
Classifier: Topic :: Utilities
Classifier: License :: OSI Approved :: MIT License
Classifier: Programming Language :: Python :: 3.11
Classifier: Programming Language :: Python :: 3 :: Only
Requires-Python: >=3.3
License-File: LICENSE.txt
